zazu/__init__.py
zazu/build.py
zazu/build_server.py
zazu/cli.py
zazu/cmake_helper.py
zazu/code_reviewer.py
zazu/config.py
zazu/credential_helper.py
zazu/git_helper.py
zazu/github_helper.py
zazu/issue_tracker.py
zazu/style.py
zazu/styler.py
zazu/upgrade.py
zazu/util.py
zazu/version.txt
zazu/cmake/arm32-linux-gnueabihf.cmake
zazu/dev/__init__.py
zazu/dev/commands.py
zazu/githooks/commit-msg
zazu/githooks/post-checkout
zazu/githooks/post-merge
zazu/githooks/pre-commit
zazu/plugins/__init__.py
zazu/plugins/astyle_styler.py
zazu/plugins/autopep8_styler.py
zazu/plugins/clang_format_styler.py
zazu/plugins/github_code_reviewer.py
zazu/plugins/github_issue_tracker.py
zazu/plugins/jira_issue_tracker.py
zazu/plugins/teamcity_build_server.py
zazu/repo/__init__.py
zazu/repo/commands.py
zazu/tool/__init__.py
zazu/tool/commands.py
zazu/tool/tool_helper.py
zazu-0.10.0.dist-info/DESCRIPTION.rst
zazu-0.10.0.dist-info/METADATA
zazu-0.10.0.dist-info/RECORD
zazu-0.10.0.dist-info/WHEEL
zazu-0.10.0.dist-info/entry_points.txt
zazu-0.10.0.dist-info/metadata.json
zazu-0.10.0.dist-info/top_level.txt
