Metadata-Version: 2.0
Name: zazu
Version: 0.10.0
Summary: A development workflow management CLI for GitHub, JIRA, and TeamCity
Home-page: https://github.com/stopthatcow/zazu
Author: Nicholas Wiles
Author-email: nhwiles@gmail.com
License: MIT
Keywords: teamcity,jira,git,github
Platform: POSIX
Platform: MacOS
Platform: Windows
Classifier: Development Status :: 3 - Alpha
Classifier: Intended Audience :: Developers
Classifier: License :: OSI Approved :: MIT License
Classifier: Operating System :: OS Independent
Classifier: Programming Language :: Python :: 2.7
Classifier: Topic :: Software Development
Classifier: Topic :: Software Development :: Build Tools
Classifier: Topic :: Software Development :: Quality Assurance
Classifier: Intended Audience :: Developers
Requires-Dist: GitPython (>=2.0.7)
Requires-Dist: Importing (>=1.10)
Requires-Dist: PyGithub (>=1.34.0)
Requires-Dist: autopep8 (>=1.2.4)
Requires-Dist: click (>=6.6)
Requires-Dist: future (>=0.16.0)
Requires-Dist: futures (>=3.0.5)
Requires-Dist: gcovr (>=3.2)
Requires-Dist: inquirer (>=2.1.7)
Requires-Dist: jira (>=1.0.10)
Requires-Dist: keyring (>=8.7)
Requires-Dist: keyrings.alt (>=2.2)
Requires-Dist: pyteamcity (>=0.1.1)
Requires-Dist: pyyaml (>=3.11)
Requires-Dist: requests (>=2.10.0)
Requires-Dist: semantic-version (>=2.5.0)
Requires-Dist: straight.plugin (>=1.4.1)
Requires-Dist: teamcity-messages (>=1.19)
Requires-Dist: pyreadline (>=2.1); sys_platform == "win32"
